{
 "title": "Livro - CRIANDO PROSPERIDADE - CHOPRA",
 "authors": [
  "CHOPRA"
 ],
 "publisher": "Alaúde",
 "price": "R$ 35,00",
 "info": "Descubra o segredo para atrair mais riqueza em sua vida. Com sabedoria clara e simples, Deepak Chopra explica que riqueza não quer dizer só dinheiro, mas também a abundância, o fluxo, a generosidade do universo. É do que precisamos para transformar cada um de nossos desejos em realidade. Para isso, Chopra apresenta 26 passos para trazer prosperidade e realização em todos os níveis de nossa vida. Segundo o autor, a riqueza é o nosso estado natural, e o universo físico, com toda a sua abundância, é fruto de um campo ilimitado de possibilidades. Através de uma série de passos simples e ações cotidianas, Criando prosperidade estimula a consciência de riqueza necessária para explorar todo o seu potencial e realizar seus maiores desejos.",
 "year": "2019",
 "isbn": "9788578815868",
 "edition": "1",
 "pages": "120",
 "language": "Português"
}