{
 "title": "Livros de Biologia e Biotecnologia - Saúde - Livraria Florence",
 "authors": "",
 "publisher": "",
 "price": "R$ 43,99",
 "info": "10% OFF\n        \n\n\n\n\nSinopse: Pela primeira vez, ao completar 50 anos de carreira, o mais importante fotógrafo de natureza do Brasil reúne em um só livro as suas melhores fotos de animais. Em perigosas madrugadas no Pantanal e na Amazônia, nas noites fechadas das chapadas ou em caminhadas sem trégua pelo sertão, Araquém Alcântara construiu um retrato surpreendente e am ...",
 "year": "",
 "isbn": "",
 "edition": "",
 "pages": "",
 "language": ""
}