{
 "title": "Livro - O Diário de Bordo da Família Grávida - Herrero",
 "authors": [
  "Luciana Herrero"
 ],
 "publisher": "",
 "price": "R$ 53,55",
 "info": "Este diário de bordo é o resultado de anos de estudo e de cursos especializados, das experiências diárias como pediatra, mãe e mulher, mas principalmente do aprendizado da autora, como gestante e mãe de duas crianças. O livro é enriquecido com o valioso depoimento de mamães e papais grávidos, além das orientações de vários especialistas.",
 "year": "2014",
 "isbn": "9788567866017",
 "edition": "1ª",
 "pages": "208",
 "language": "Português"
}