{
 "title": "Livro Veg Refeições Fáceis e Deliciosas Para Todos - Oliver - Companhia de Mesa",
 "authors": [
  "Jamie Oliver"
 ],
 "publisher": "Companhia de Mesa",
 "price": "R$ 119,90",
 "info": "Em seu novo livro, Jamie Oliver ensina deliciosos pratos vegetarianos. Massas, curries, tortas, assados e petiscos diversos são apresentados em receitas simples, que farão você salivar, provando como pode ser saborosa uma alimentação sem carne.\n \nCada vez mais pessoas desejam aumentar o consumo de legumes e verduras no dia a dia seja pela saúde, pelo preço ou pelo planeta. Pensando nisso, Jamie Oliver criou um livro recheado de receitas à base de vegetais. Com inspirações do mundo todo, estes pratos incríveis e fáceis de fazer são uma verdadeira celebração da comida vegetariana e trarão a você a sensação de saciedade, satisfação e felicidade. Ideal para quem quer ficar um ou dois dias da semana sem carne, adotar uma alimentação vegetariana ou simplesmente experimentar novas combinações de sabores, Veg é uma fonte de inspiração e um guia para uma vida mais verde.",
 "year": "2021",
 "isbn": "9786586384116",
 "edition": "1ª",
 "pages": "312",
 "language": "Português"
}