{
 "title": "Ansiedade Um Obstáculo - Entre o homem e a felicidade",
 "authors": [
  "Cecil A. Poole, F.R.C."
 ],
 "publisher": "Rosacruz",
 "price": "R$ 48,00",
 "info": "Nós últimos anos se têm escrito muitos livros do tipo chamado ' faça você mesmo\". Eles abordam toda sorte de condições e circunstâncias; explicam como fazer consertos em casa ou como ser seu próprio psiquiatra. Abordam o mundo físico em que vivemos e também lidam com especulações para os que carecem das aptidões ou do treinamento para usá-los. formato 16 x 23 cm . Brochura com sobre capa. Loja 1, Prédio 1° andar",
 "year": "1979",
 "isbn": "19791174",
 "edition": "1ª Edição",
 "pages": "174",
 "language": "Português"
}