{
 "title": "500 Adesivos Marvel Vingadores - Book7: Livros, Bíblias, Bíblias Personalizadas, Cadernos, Agendas, Calendários e muito mais.",
 "authors": "Rodrigues, Naihobi S.",
 "publisher": "",
 "price": "R$ 109,00",
 "info": "Descrição \n                Com Este Livro As Crianças Vão Se Divertir Pra Valer. Ele Vem Com Um Perfil dos Vingadores, Desenhos para Colorir, Atividades e Com Mais de 500 Adesivos para Colar Aonde Quiser.",
 "year": "2017",
 "isbn": "9788594720818",
 "edition": "1",
 "pages": "44",
 "language": ""
}