{
 "title": "Protetores, Os - Vol. 02 + Marca Página - Book7: Livros, Bíblias, Bíblias Personalizadas, Cadernos, Agendas, Calendários e muito mais.",
 "authors": "",
 "publisher": "",
 "price": "R$ 160,00",
 "info": "Descrição \n                Depois de anos vivendo como uma pessoa normal e se escondendo entre a multidão, VIP se depara com o maior desafio de sua vida: recrutar um novo grupo de heróis e lutar contra a Matilha. Na sequência dos acontecimentos de Os Protetores",
 "year": "",
 "isbn": "7803965851297",
 "edition": "32",
 "pages": "",
 "language": ""
}