{
 "title": "Anatomia da Musculação",
 "authors": [
  "Nick Evans"
 ],
 "publisher": "MANOLE",
 "price": "",
 "info": "Esta Segunda Edição do Best-Seller Anatomia da Musculação Apresenta Ilustrações Totalmente Reformuladas e Novos Exercícios. Concentrando-Se Nos Principais Grupos Musculares dos Ombros, Tórax, Costas, Membros Superiores e Inferiores, Abdominais, e Focalizando Zonas Musculares e Áreas Difíceis de Trabalhar, Esta Obra Faz a Diferença Entre O Simples Ganho de Massa e a Escultura de Um Corpo Digno de Concurso Fitness.  Com Ilustrações Anatômicas Detalhadas e Coloridas, Instruções Passo a Passo e Informações Sobre Os Músculos Primários e Secundários Trabalhados Em Cada Exercício, Esta É a Obra Ideal para Ajudá-Lo a Modelar Seu Físico de Uma Forma Jamais Imaginada. O Verdadeiro Segredo Está Em Conhecer a Anatomia para que Se Possa Modificá-La da Maneira Desejada.  Todos Os Exercícios Praticados Em Uma Academia São Abordados e Qualquer Um Deles Poderá Ser Consultado Em Menos de Cinco Minutos. Trata-Se de Um Guia Prático Com 100 Exercícios e 104 Variações Acompanhados de Discussões Técnicas e Ilustrações de Alta Qualidade.  É Uma Referência para Fisiculturistas, Atletas, Praticantes de Musculação, Alunos e Professores de Educação Física e Ciências do Esporte.",
 "year": "2017",
 "isbn": "9788520453711",
 "edition": "240",
 "pages": "240",
 "language": ""
}