{
 "title": "A Testemunha - Book7: Livros, Bíblias, Bíblias Personalizadas, Cadernos, Agendas, Calendários e muito mais.",
 "authors": "Roberts, Nora",
 "publisher": "",
 "price": "R$ 109,00",
 "info": "Descrição \n                Paixões Tórridas e Suspense de Primeira No Novo Livro da Autora Best-Seller Mundial   Fruto de Uma Inseminação Artificial e Criada Por Uma Mãe Fria e Controladora, Elizabeth Fitch Se Deixa Levar Por Uma Noite. Depois de Beber Além da Conta, Ela Se Encanta Por Um Homem Galante e Dono de Um Sedutor Sotaque Russo. Acompanhando a Amiga Julie, Segue Rumo a Uma Linda Mansão Em Lake Shore Drive, Ainda Sem Saber que O Lugar Alteraria para Sempre Sua Vida. Doze Anos Mais Tarde, No Interior do Arkansas, Uma Nova Moradora Anda Despertando a Curiosidade da Vizinhança. Abigail Lowery Não É Propriamente Uma Recém-Chegada, Mas Continua Sendo Uma Desconhecida: Em Um Ano, Sabe-Se Pouco, Ou Quase Nada, Sobre a Moça.  O Mistério de Abigail Lowery e Sua Mente Afiada, Natureza Secreta e Filosofia de Vida Nada Romântica Intriga O Chefe de Polícia Local, Brooks Gleason, Tanto a Nível Pessoal Quanto Profissional. Mas Enquanto Suspeita que Abigail Precisa de Proteção Contra Algo, Gleason, Acostumado a Criminosos de Segunda Categoria, Não Faz Ideia de que Homens Poderosos e Perigosos O Observam e Mantêm Sob Sua Mira. e Abigail Lowery, que Construiu Uma Vida Baseada Em Segurança e Autocontrole, Corre O Risco de Perder Ambos.",
 "year": "2015",
 "isbn": "9788528620344",
 "edition": "2",
 "pages": "476",
 "language": ""
}