{
 "title": "Agora e Viver - Book7: Livros, Bíblias, Bíblias Personalizadas, Cadernos, Agendas, Calendários e muito mais.",
 "authors": "",
 "publisher": "",
 "price": "R$ 109,00",
 "info": "Descrição \n                Filha de João Flávio Lemos de Moraes, empresário milionário que mergulhou fundo nas drogas e quase chegou a ser preso nos EUA na década de 1990, a bela Isabella Lemos de Moraes passa a limpo a história de sua família em Agora É Viver, um relato sincero e corajoso que pretende ajudar milhares de famílias a superar a codependência. Mais velha de quatro irmãos, Isabella relembra o inferno pessoal e familiar que a levou a desenvolver anorexia, bulimia, depressão e pânico, até entender, com a ajuda da psicanálise, que apesar de não usar drogas sua vida foi profundamente afetada por um dependente químico.",
 "year": "",
 "isbn": "9788532528360",
 "edition": "239",
 "pages": "",
 "language": ""
}