{
 "title": "Simon'S Cat: As Aventuras de Um Gato Travesso e Comilão - Book7: Livros, Bíblias, Bíblias Personalizadas, Cadernos, Agendas, Calendários e muito mais.",
 "authors": "Tofield, Simon",
 "publisher": "",
 "price": "R$ 109,00",
 "info": "Descrição \n                Esta Obra Pretende Retratar a Relação Entre Um Homem e Seu Gato. As Aventuras Diárias Deste Animal de Estimação Adorável, que Deseja Sempre Mais Comida, e Seu Exasperado Mas Delirante Dono Ganham Vida Por Meio Deste Livro Ilustrado.",
 "year": "2012",
 "isbn": "9788525425997",
 "edition": "1",
 "pages": "240",
 "language": ""
}