{
 "title": "360 Dias de Sucesso",
 "authors": [
  "Thalita Reboucas"
 ],
 "publisher": "ROCCO",
 "price": "R$ 19,63",
 "info": "Um grupo de amigos que só queriam levar um som e se divertir veem suas vidas virar de cabeça para baixo quando publicam um vídeo na internet e se tornam sucesso imediato na rede. Retratando um fenômeno comum no meio artístico e ainda mais frequente em tempos de internet - a fama instantânea e efêmera. Um livro divertido e emocionante sobre sonhos, ídolos, romance, traição, escolhas. E, claro, muita música.",
 "year": "",
 "isbn": "9788579802201",
 "edition": "304",
 "pages": "304",
 "language": ""
}