{
 "title": "Estampas mágicas: Livro para colorir antiestresse",
 "authors": [
  "Jenean Morrison"
 ],
 "publisher": "BAZAR EDITORIAL",
 "price": "R$ 21,35",
 "info": "Os Grandes Trabalhos da Artista Jenean Morrison, Uma das Maiores Experts Em Design de Tecidos, Estampas e Arte Abstrata dos Eua, Saem das Telas Especialmente para As Páginas Deste Livro! Relaxar, Descansar a Mente e Expandir Sua Criatividade Nunca Foi Tão Divertido! 50 Desenhos Elaborados Com Estampas Florais, Padrões Geométricos e Abstratos, Com Diferentes Níveis de Dificuldade - do Fácil ao Bastante Desafiador -, Oferecem Experiências Mágicas a Coloristas de Todas As Idades! Desenhos Impressos Apenas Na Frente das Páginas, Assim Você Pode Liberar Toda a Sua Criatividade Sem Medo da Tinta Vazar para O Verso da Folha! Estampas Mágicas Vai Encantar Você! Aventure-Se Na Arte de Colorir e Mergulhe Em Um Universo Mágico, Em que Você É O Criador de Verdadeiras Obras de Arte! Nestes Momentos de Liberdade Você Pode Se Distanciar das Preocupações Cotidianas, das Pressões e do Estresse e Se Lançar ao Desafio de Se Divertir! Colorir É Uma das Mais Agradáveis Opções de Relaxamento, e Pode Ser Praticada Tanto Individualmente, Nos Seus Momentos Particulares, Como Em Conjunto Com Aqueles que Você Gosta!´5 Minutos Por Dia Colorindo para Encontrar a Calma Interior!´ Mais Relaxante que Praticar Um Esporte, Mais Divertido do que Um Psiquiatra, Mais Barato do que Um Spa: Colorir É Uma Solução para Todos para Aliviar O Estresse e Relaxar Criando!",
 "year": "2015",
 "isbn": "9788563795120",
 "edition": "1",
 "pages": "104",
 "language": ""
}