{
 "title": "Hiperfoco - Book7: Livros, Bíblias, Bíblias Personalizadas, Cadernos, Agendas, Calendários e muito mais.",
 "authors": "Bailey, Chris",
 "publisher": "",
 "price": "R$ 55,00",
 "info": "Descrição \n                Você Tem Mil e Uma Tarefas ao Longo do Dia, Seja No Trabalho Ou Na Vida Pessoal. Mas Muitas Vezes, Logo que Começa Uma Delas, É Interrompido Por Uma Mensagem No Celular Ou Por Alguém que Te Chama. Às Vezes, Você Mesmo Se Cansa da Tarefa e Resolve Checar Uma Rede Social. e Aí Entra Numa Espiral de Distrações e Nunca Consegue Finalizar O que Começou. Parece Familiar? Todo Mundo Sofre Com a Falta de Foco Hoje Em Dia. Nossa Atenção Se Divide Entre Coisas Demais, E, Embora Estejamos Sempre Ocupados, Rendemos Pouco. Será que É Possível Reverter Esse Cenário e Nos Tornarmos Mais Produtivos, Fazendo Mais Em Menos Tempo? Neste Livro, O Especialista Em Produtividade Chris Bailey Fornece Dicas Práticas que Nos Ajudam a Controlar Melhor Nossa Atenção. Ele Revela Como O Cérebro Alterna Entre O Modo Hiperfoco (Um Estado de Profunda Concentração) e O Modo Foco Disperso (Ideal para Despertar a Criatividade), e que O Caminho para Sermos Mais Eficientes e Criativos É Saber Combinar Os Dois Na Medida Certa. Hiperfoco Vai Mudar Definitivamente O Modo Como Você Trabalha.",
 "year": "2019",
 "isbn": "9788557173040",
 "edition": "1",
 "pages": "256",
 "language": ""
}