{
 "title": "A Vida e As Aventuras de Nicholas Nickleby - Book7: Livros, Bíblias, Bíblias Personalizadas, Cadernos, Agendas, Calendários e muito mais.",
 "authors": "Dickens, Charles",
 "publisher": "",
 "price": "R$ 109,00",
 "info": "Descrição \n                A Família do Jovem Nicholas Nickleby Parte para Londres Após a Morte do Patriarca, Profundamente Endividado, Deixá-La Na Miséria. Na Metrópole, Os Nickleby Buscam O Auxílio de Um Parente Abastado, Mas de Caráter Duvidoso, Com Quem Nicholas Logo Se Indispõe. Desamparado, Resta ao Rapaz Forjar Seu Próprio Caminho, Deparando Com Empregos Ultrajantes e Abusos, Mas Também Com Amigos Leais e Vocações Surpreendentes.  Neste que É Um de Seus Romances Mais Excêntricos, Charles Dickens Explora Uma Rica Galeria de Tipos Marcantes ? Falsos Pedagogos, Órfãos Desamparados, Larápios, Atrizes e Vedetes ?, Num Retrato Ora Mordaz, Ora Bem-Humorado da Sociedade Inglesa No Século Xix.",
 "year": "2017",
 "isbn": "9788520437155",
 "edition": "912",
 "pages": "912",
 "language": ""
}