{
 "title": "Novena das almas + Marca Página",
 "authors": [
  "false"
 ],
 "publisher": "SANTUÁRIO",
 "price": "",
 "info": "A tradição cristã cultiva entre outras coisas o culto aos mortos. Rezar pelos mortos, pelos entes queridos que já se foram, é algo que desde muito cedo se cultiva no catolicismo. Nessa novena, o autor nos convida a rezar por nossos irmãos, que já partiram desta vida, e elevar nossa prece ao Deus de infinito amor.",
 "year": "2015",
 "isbn": "7803029185559",
 "edition": "32",
 "pages": "32",
 "language": ""
}