{
 "title": "A Saga do Batman Vol. 2",
 "authors": [
  "Max Allan Collins",
  "Mike W. Bar"
 ],
 "publisher": "PANINI",
 "price": "",
 "info": "Graves ferimentos sofridos pelo Menino-Prodígio após um combate da Dupla Dinâmica com o Chapeleiro Louco levam Batman a refletir sobre o passado e o futuro de sua parceria com Jason Todd, o segundo garoto a usar a identidade de Robin. As dúvidas do Homem-Morcego aumentarão ainda mais conforme ele se aprofunda em outros elementos da vida pregressa do jovem, como a relação dele com o Duas-Caras e um estranho orfanato de Gotham.Detective Comics 572-574, Batman 408-410",
 "year": "2022",
 "isbn": "9786555129793",
 "edition": "1",
 "pages": "176",
 "language": ""
}