{
 "title": "Hematologia - Book7: Livros, Bíblias, Bíblias Personalizadas, Cadernos, Agendas, Calendários e muito mais.",
 "authors": "",
 "publisher": "",
 "price": "R$ 295,00",
 "info": "Descrição \n                A Série Análises Clínicas e Toxicológicas é uma coletânea de livros na área de análises clínicas e toxicológicas que aborda os métodos empregados para o diagnóstico laboratorial de doenças e a interpretação dos resultados para garantir a qualidade analítica e a adequada orientação ao paciente. Esta obra foi idealizada para ser usada por estudantes e profissionais da área de saúde como fonte de consulta. A sua leitura permitirá aprender, revisar ou aprimorar os conhecimentos sobre as questões analíticas, bem como a interpretação de seus resultados na área de análises clínicas e toxicológicas.Os principais temas abordados são: hematologia, bioquímica, imunologia, hormônios, citologia, parasitologia, biologia molecular, microbiologia e micologia e toxicologia ocupacional.A obra Hematologia – Métodos e Interpretação consiste em um guia para consultas diárias, objetivas e eficientes realizadas por estudantes e profissionais.Apresenta uma abordagem atualizada da conceituação fisiopatológica, de métodos executados na rotina laboratorial e do diagnóstico laboratorial para diversas doenças hematológicas, além de imagens e ilustrações que auxiliam o entendimento.",
 "year": "",
 "isbn": "9788541201384",
 "edition": "480",
 "pages": "",
 "language": ""
}