{
 "title": "A Bela Borboleta - Book7: Livros, Bíblias, Bíblias Personalizadas, Cadernos, Agendas, Calendários e muito mais.",
 "authors": "Pinto, Ziraldo Alves",
 "publisher": "",
 "price": "R$ 55,00",
 "info": "Descrição \n                O Gato de Botas convocou os personagens de outras histórias para um salvamento muito importante. Branca de Neve, os Sete Anões, Peter Pan, o Príncipe Encantado, o Coelho do Relógio e até o Patinho Feio armaram-se de puas, pinças e tesouras, prontos para libertar a borboleta mais linda do mundo, presa no meio de um livro.",
 "year": "2009",
 "isbn": "9788506057834",
 "edition": "1",
 "pages": "32",
 "language": ""
}