{
 "title": "COZINHA DE ESTAR - 1ªED.(2016)",
 "authors": [
  "Rita Lobo"
 ],
 "publisher": "Senac SP",
 "price": "R$ 91,80",
 "info": "Mais do que um livro de receitas, Cozinha de estar é um guia para quem vai cozinhar para receber. Rita Lobo transforma sala e cozinha em uma coisa só, um ambiente aconchegante e espaçoso, onde cabe todo mundo — e de onde ninguém quer sair! Ganhador do prêmio internacional Gourmand e finalista do prêmio Jabuti, o livro apresenta as regras tradicionais para planejar um jantar ou uma festinha em casa, e também mostra como deixar tudo mais informal. Ou não, quem escolhe é você! Mas uma coisa é certa: para receber bem, não é preciso ter pompa nem prataria. Esta edição ampliada vem com um Natal de presente: inclui um capítulo novo, com receitas e dicas para uma ceia completa, cheia de inspiração tropical. Afinal, nosso Natal é no verão — e nosso verão é um forno preaquecido em temperatura máxima! Um colorido só, bem brasileiro. Divirta-se! Cozinhar é libertador.",
 "year": "2016",
 "isbn": "9788539611041",
 "edition": "1ª",
 "pages": "272",
 "language": "Português"
}