{
 "title": "O ALMANAQUE DE FRAN LEBOWITZ - 1ªED.(2022)",
 "authors": [
  "Fran Lebowitz"
 ],
 "publisher": "Todavia",
 "price": "R$ 74,90",
 "info": "Quando a Netflix exibiu a série Faz de conta que NY é uma cidade, de Martin Scorsese, muita gente no Brasil foi apresentada pela primeira vez a Fran Lebowitz. Artista brilhante com humor ácido, publicou pouquíssimo, apenas três livros, e nenhum no Brasil. A obra reúne textos de dois desses livros: Metropolitan Life e Social Studies, originalmente publicados em 1978 e 1981 a partir da coluna que ela assinava na Interview, revista fundada por Andy Warhol.",
 "year": "2022",
 "isbn": "9786556922997",
 "edition": "1ª",
 "pages": "288",
 "language": "Português"
}