{
 "title": "INCERTEZA QUANTICA: OS MISTERIOS DE UMA TEORIA E A NOVA ERA DA INFORMAÇAO - 1ªED.(2022)",
 "authors": [
  "Rafael Chaves"
 ],
 "publisher": "Zahar",
 "price": "R$ 89,90",
 "info": "Este livro oferece um panorama amplo e acessível da mais bem-sucedida teoria da física — sua história, seus conceitos fundamentais e como vem mudando o futuro.Concebida há mais de um século, a teoria quântica explica desde os constituintes fundamentais da matéria até fenômenos astrofísicos e cosmológicos. Nenhuma outra foi tão precisa na predição de resultados de experimentos. Hoje testemunhamos uma segunda revolução quântica, e efeitos quânticos já podem ser utilizados para processar, armazenar, criptografar e transmitir informação — e de forma tão segura que mesmo o melhor dos hackers demoraria bilhões de anos para violá-la.Do famoso experimento da fenda dupla de Thomas Young à realidade do chip quântico de 53 qubits da Google, o autor percorre mais de cem anos de evolução científica, apresentando algumas das mais extraordinárias descobertas. Com um texto envolvente e nada hermético, o físico Rafael Chaves — cientista de ponta brasileiro e, em suas próprias palavras, um hacker da informação quântica — consegue transpor em palavras o vasto, elegante e incerto universo da quântica.",
 "year": "2022",
 "isbn": "9786559790784",
 "edition": "1ª",
 "pages": "376",
 "language": "Português"
}