{
 "title": "BATMAN E ROBIN - 1ª TEMPORADA COMPLETA (QTD: 6)",
 "authors": [],
 "publisher": "Line Store",
 "price": "R$ 94,90",
 "info": "O rico empresário Bruce Wayne (Adam West) e seu amigo Dick Grayson (Burt Ward) levam uma vida dupla: Eles são, na verdade, a dupla Batman e Robin, combatentes do crime. Uma passagem secreta na mansão Wayne leva à Bat-Caverna, onde o Comissário Gordon (Neil Hamilton) frequentemente faz contato com a dupla, pelo Bat-Fone, com as últimas emergências que afligem Gotham City. Chegando à cena do crime no Bat-Móvel, Batman e Robin devem lidar com uma imensa variedade de criminosos, incluindo o Charada, o Coringa, a Mulher-Gato e o Pinguim.DISCO 11 Charada é uma Charada2 Destruído com um Soco3 Pinguim-O Ladrão de Casaca4 Pinguim Pega um Peixão5 Coringa, O Selvagem6 Batman Está IrritadoDISCO 27 Descongelamento Instantâneo8 Ratos Gostam de Queijo9 Zelda, a Grande10 Zelda Levou a Pior11 Uma Charada por Dia Aposenta um Charadista12 Quando os Ratos Estão Longe, os Camundongos FolgamDISCO 313 O Décimo Terceiro Chapéu14 Batman Reage15 O Coringa Vai à Escola16 Um Adversário à Altura de um Medonho Bandido17 Falso ou Verdadeiro18 Corrida dos RatosDISCO 419 O Crime Perfeito20 Melhor Sorte na Próxima Vez21 O Pinguim Regenerado22 Desta Vez Ainda Não23 O Anel de Cera24 Baixa a Lenha NeleDISCO 525 O Traça Traça um Ataque26 Gotham City Pega Fogo27 A Maldição de Tut28 A Arapuca29 O Traça-Traça do MassacreDISCO 630 Batman Dá Carta31 Morte em Câmera Lenta32 O Charada Dá Um Passo em Falso33 Inimigos de Águas Turvas34 Batman Arma o Cenário",
 "year": "850 MINUTOS",
 "isbn": "7898673124542",
 "edition": "6",
 "pages": "FULLSCREEN 4:3 (1,33:1)",
 "language": "Espanhol, Inglês, Português"
}