{
 "title": "QUATRO CINCO UM (451) #60 - 1ªED.(2022)",
 "authors": [],
 "publisher": "Quatro Cinco um",
 "price": "R$ 32,00",
 "info": "A Quatro Cinco Um é uma revista voltada a quem lê livros sem parar. Mensalmente, cobre cerca de 20 áreas com resenhas e serviços sobre cerca de 100 livros recém-lançados. A 60a. edição traz o especial “Histórias pantaneiras”, sobre o Pantanal. Arte da capa: João Farkas.O especial inclui textos sobre um século de destruição da região, a boiada que passa sobre a legislação ambiental, as origens do Pantanal segundo seus habitantes mais antigos, a comida e a literatura pantaneira, o poeta Manoel de Barros, além de um depoimento do fotógrafo que estava no local durante as queimadas históricas de 2020, um ensaio fotográfico do bioma e um listão com uma seleção de livros sobre a região.A edição traz ainda uma entrevista com Paulina Chiziane, uma reportagem sobre Cida Bento, as palavras finais de Joan Didion e Janet Malcolm, análises sobre como manter a floresta em pé e como a violência contra a mulher é usada como mecanismo de controle. Traz também textos sobre a bomba de Hiroshima pelos olhos de Tamiki Hara, a perseguição da ditadura militar aos bailes soul do Rio nos anos 70, o terremoto que mudou o mundo, o livro sobre aborto de Annie Ernaux nos cinemas, um inventário de Gilberto Gil e mais.A edição tem 25 livros destacados, um listão com 103 lançamentos em 22 áreas e um listão especial sobre o Pantanal com 18 livros.",
 "year": "2022",
 "isbn": "977252655800600060",
 "edition": "1ª",
 "pages": "48",
 "language": "Português"
}