{
 "title": "50 Mulheres para Se Inspirar",
 "authors": [
  "Alice Ramos"
 ],
 "publisher": "Ciranda Cultural",
 "price": "R$ 24,90",
 "info": "Conheça neste livro grandes personalidades femininas que enfrentaram todo tipo de desafio e dificuldade para conquistar seu espaço no mundo e deixar seu legado. São incríveis histórias de perseverança, força e superação que vão inspirar você a encontrar e a lutar pela sua própria causa",
 "year": "2021",
 "isbn": "9786555004311",
 "edition": "1",
 "pages": "112",
 "language": "Português"
}