{
 "title": "A Arte do Romance",
 "authors": [
  "Milan Kundera"
 ],
 "publisher": "Companhia das Letras",
 "price": "R$ 62,90",
 "info": "Primeiro livro de não ficção do autor de A insustentável leveza do ser, A arte do romance é a confissão nascida da experiência prática do romancista. Nele são discutidas em profundidade a evolução do romance e seus aspectos centrais (de Cervantes a Proust, passando por Hermann Broch e Kafka), pelo olhar subjetivo de um artífice que vê ameaçada a continuidade de seu trabalho. Escritos ainda sob o forte impacto da crítica francesa da época do Nouveau Roman e dos ataques pós-modernos, os ensaios procuram restaurar o sentido do romance como gênero autônomo, após o esgotamento da experimentação modernista, sem ceder às tentações que desejavam a recuperação da narrativa romanesca do século XIX.",
 "year": "2016",
 "isbn": "9788535927986",
 "edition": "1",
 "pages": "168",
 "language": "Português"
}