{
 "title": "Buda - Vol.1",
 "publisher": "Editora JBC",
 "price": "R$ 42,00",
 "info": "Épico e emocionante! A jornada do príncipe Siddartha, desde o seu nascimento até alcançar a iluminação, é contada sob a ótica e a arte genial de Osamu Tezuka. Aclamado pela crítica e pelo público, Buda (Buddha) levou mais de 10 anos sendo produzido por Teazuka, de 1972 até 1983. Nascido em meio ao luxo palaciano na antiga Índia, Siddartha tinha saúde frágil e ainda em seus primeiros dias de vida tornou-se órfão de mãe. Mas foi quando, já adulto, se deparou com a pobreza e as guerras que atingiam a sua nação, que ele decidiu partir em sua jornada espiritual para encontrar o verdadeiro sentido da vida e ajudar ao maior número de pessoas a encontrar esperança onde já não mais havia. Compilada em 8 volumes para esta Coleção Especial, Buda é mais uma obra indispensável do “pai dos mangás”.",
 "authors": [
  "Osamu Tezuka"
 ],
 "year": "2022",
 "isbn": "978-6555942378",
 "edition": "1ª",
 "pages": "400",
 "language": "Português"
}