{
 "title": "AS MENTIRAS QUE NOS UNEM",
 "publisher": "ARQUEIRO",
 "price": "R$ 40,00",
 "info": "Autora best-seller do The New York Times com mais de 11 milhões de livros vendidos.\n                \n                \n                \"Emily tem uma habilidade única para capturar a complexidade das emoções humanas enquanto narra uma história arrebatadora.\" – The Washington Post\n                \n                \n                \n                    Uma encantadora e emocionante história sobre a nossa eterna busca pelo amor e pela verdade.\n                \n                \n                \n                Decidida a se tornar jornalista, Cecily Gardner se mudou para Nova York. Quatro anos depois, prestes a fazer 30 anos e sem perspectivas, ela se vê num bar, questionando se algum dia sua carreira vai deslanchar e se terminar com o namorado foi realmente uma boa ideia.\n                \n                No momento em que vai ligar para ele, um homem se senta ao seu lado e a impede. Grant é engraçado e atraente e os dois logo sentem uma conexão arrebatadora, que Cecily nunca teve com ninguém antes. Pela primeira vez, ela decide seguir o coração em vez da razão e mergulhar de cabeça no novo relacionamento.\n                \n                Poucos meses depois, no dia 11 de setembro de 2001, as torres do World Trade Center são atingidas e, no meio do caos, Grant desaparece.\n                \n                Cecily começa a procurá-lo, mas acaba descobrindo que não é a única pessoa que está atrás de Grant. Ela decide investigar a fundo, mas as perguntas não param de surgir: será que Cecily conhece Grant de verdade? É possível amar uma pessoa que não é quem você achava que era?",
 "authors": [],
 "year": "",
 "isbn": "",
 "edition": "",
 "pages": "",
 "language": ""
}