{
 "title": "A FELICIDADE É INÚTIL",
 "publisher": "CITADEL",
 "price": "R$ 19,92",
 "info": "ESTE LIVRO NÃO ENSINA NINGUÉM A SER FELIZ.\n                \nTampouco a viver momentos de felicidade. Também ficarei devendo alguma fórmula para medir ou simplesmente diagnosticar a felicidade própria ou alheia. No entanto, ao longo das páginas, aqui e acolá, pode haver algum prazer. Uma satisfação decorrente da graça de uma ideia, da pertinência de algum exemplo.\nAo afirmar que a felicidade é inútil, não sugiro que ela não tenha valor. Que seja ruim. Que não valha a pena persegui-la ou entender do que se trata. Pelo contrário. O inútil pode ser bom. Não prestar pra nada pode indicar uma preciosidade inestimável. O bem supremo.\n Aqui você se coça:\n– Como assim? Onde pode estar o valor de uma coisa que não presta pra nada?\n Se esse questionamento não lhe interessa, se o que você espera da leitura de algo com “felicidade” no título não coincide com o que este livro promete, melhor recolocá-lo na estante.\nAgora, se a ideia de uma coisa inútil ser preciosa desperta uma inquietação em você, vá para o caixa.",
 "authors": [
  "CLÓVIS DE BARROS FILHO"
 ],
 "year": "2019",
 "isbn": "6550470226",
 "edition": "1",
 "pages": "288",
 "language": "PORTUGUÊS"
}